README
setup.py
bin/start_broker.py
bin/start_scheduler.py
bin/start_worker.py
siblings/__init__.py
siblings/aligner.py
siblings/common.py
siblings/conversion.py
siblings/dataimport.py
siblings/db.py
siblings/pymixin.py
siblings/rest.py
siblings/scheduler.py
siblings/server.py
siblings/settings.py
siblings/tablesformat.py
siblings/visit.py
siblings/zmq.py
siblings.egg-info/PKG-INFO
siblings.egg-info/SOURCES.txt
siblings.egg-info/dependency_links.txt
siblings.egg-info/requires.txt
siblings.egg-info/top_level.txt
siblings/test/TestDb.h5
siblings/test/__init__.py
siblings/test/test_aligner.py
siblings/test/test_db.py
siblings/test/test_rest.py
siblings/test/test_scheduler.py
siblings/test/test_zmq.py