Metadata-Version: 1.1
Name: siblings
Version: 0.4.0
Summary: Siblings is a code base to compute homologs between genomes and make them publicly available through a REST api
Home-page: http://siblings.ch
Author: Adrian Altenhoff
Author-email: adrian.altenhoff@inf.ethz.ch
License: MPL 2.0
Keywords: bioinformatics homology homologs Smith-Waterman resource REST
Platform: UNKNOWN
Classifier: Development Status :: 3 - Alpha
Classifier: Intended Audience :: Developers
Classifier: Intended Audience :: Science/Research
Classifier: Topic :: Scientific/Engineering :: Bio-Informatics
Classifier: License :: OSI Approved :: Mozilla Public License 2.0 (MPL 2.0)
Classifier: Programming Language :: Python :: 2
Classifier: Programming Language :: Python :: 2.7
Classifier: Programming Language :: Python :: 3
Classifier: Programming Language :: Python :: 3.3
Classifier: Programming Language :: Python :: 3.4
